pyboundfit/__init__.py
pyboundfit/boundfit_adaptive_splines.py
pyboundfit/boundfit_poly.py
pyboundfit/demo.py
pyboundfit/fun_residuals_spl.py
pyboundfit/numsplines.py
pyboundfit/robust_std.py
pyboundfit/version.py
pyboundfit/tests/test_demo.py
pyboundfit-0.3.0.dist-info/LICENSE.txt
pyboundfit-0.3.0.dist-info/METADATA
pyboundfit-0.3.0.dist-info/WHEEL
pyboundfit-0.3.0.dist-info/top_level.txt
pyboundfit-0.3.0.dist-info/RECORD
