Metadata-Version: 2.2
Name: pyboundfit
Version: 0.3.0
Summary: Boundary fits using polynomials or splines
Author-email: Nicolás Cardiel <cardiel@ucm.es>
License: GPL-3.0-or-later
Project-URL: Homepage, https://github.com/nicocardiel/pyboundfit
Project-URL: Repository, https://github.com/nicocardiel/pyboundfit.git
Classifier: Programming Language :: Python :: 3.9
Classifier: Programming Language :: Python :: 3.10
Classifier: Programming Language :: Python :: 3.11
Classifier: Programming Language :: Python :: 3.12
Classifier: Programming Language :: Python :: 3.13
Classifier: Development Status :: 3 - Alpha
Classifier: Environment :: Console
Classifier: Intended Audience :: Science/Research
Classifier: License :: OSI Approved :: GNU General Public License (GPL)
Classifier: Operating System :: OS Independent
Classifier: Topic :: Scientific/Engineering :: Astronomy
Requires-Python: >=3.9
License-File: LICENSE.txt
Requires-Dist: lmfit
Requires-Dist: matplotlib
Requires-Dist: numpy
Requires-Dist: scipy
Provides-Extra: test
Requires-Dist: pytest; extra == "test"
